plugget/__init__.py
plugget/_utils.py
plugget/settings.py
plugget/actions/_copy_files.py
plugget/actions/_max3ds_utils.py
plugget/actions/_maya_utils.py
plugget/actions/_requirements.py
plugget/actions/_template.py
plugget/actions/_utils.py
plugget/actions/blender_addon.py
plugget/actions/blender_requirements.py
plugget/actions/krita_plugin.py
plugget/actions/krita_requirements.py
plugget/actions/max3ds_macroscript.py
plugget/actions/max3ds_plugin.py
plugget/actions/max3ds_requirements.py
plugget/actions/maya_module.py
plugget/actions/maya_plugin.py
plugget/actions/maya_requirements.py
plugget/actions/substance_painter_plugin.py
plugget/actions/substance_painter_requirements.py
plugget/actions/unreal_plugin.py
plugget/actions/unreal_requirements.py
plugget/actions/unreal_utils.py
plugget/commands/__init__.py
plugget/data/__init__.py
plugget/data/package.py
plugget/data/packages_meta.py
plugget/github/__init__.py
plugget/github/async.py
plugget/gumroad/__init__.py
plugget/resources/config.json
plugget/vendor/__init__.py
plugget/vendor/py_pip/__init__.py
plugget-0.1.17.dist-info/licenses/LICENSE
plugget-0.1.17.dist-info/METADATA
plugget-0.1.17.dist-info/WHEEL
plugget-0.1.17.dist-info/top_level.txt
plugget-0.1.17.dist-info/RECORD
