Metadata-Version: 2.4
Name: plugget
Version: 0.1.17
Summary: a package manager to install packages in your app
Author: Hannes Delbeke
Project-URL: Homepage, https://github.com/plugget/plugget
Project-URL: Source, https://github.com/plugget/plugget
Keywords: plugin,addon,add-on,extension,package,manager,resource,studio,dcc,app,application,pipeline,blender,krita,max
Classifier: Programming Language :: Python :: 3.7
Requires-Python: >=3.4
License-File: LICENSE
Requires-Dist: importlib-metadata; python_version < "3.7"
Requires-Dist: detect-app
Requires-Dist: py-pip
Requires-Dist: requests
Dynamic: license-file
